{"note":"Don't delete this file! It's used internally to help with page regeneration.","name":"simpleT","google":"","tagline":"Simple Template Engine for Node.js","body":"# simpleT 0.0.8\r\n\r\nsimpleT is a simple template engine for node.js that has some special features:\r\n\r\n- Simple structure with minimum configuration\r\n- Embedded JavaScript support\r\n- Client-side support\r\n- High performance\r\n- Customizable code delimiters\r\n- Global values injection\r\n- Caching\r\n- Includes\r\n- Automatic HTML characters escape\r\n- Result without redundant whitespace\r\n\r\nTested with node.js 0.8+\r\n\r\n*THIS DESCRIPTION IS NOT COMPLETE, MORE CONTENT WILL BE ADDED*\r\n\r\n### [Documentation](https://github.com/micnic/simpleT/wiki/Documentation \"simpleS Documentation\")\r\n\r\n#### More simple modules\r\n[simpleS](http://micnic.github.com/simpleS/)\r\n\r\n## Instalation\r\n\r\n\tnpm install simplet\r\n\r\n## Usage\r\n\r\n```javascript\r\nvar simplet = require('simplet');\r\nvar stringEngine = simplet({\r\n    close: '}}',\r\n    open: '{{'\r\n});\r\n\r\nstringEngine.render({\r\n\tid: 'test',\r\n\tcontent: 'Hello {{=name}}'\r\n}, {\r\n    name: 'me'\r\n});\r\n```\r\n\r\nor\r\n\r\n```javascript\r\n/* ***template.ejs***\r\n\r\nHello <% print(name) %>\r\n\r\n*/\r\n\r\nvar fileEngine = simplet();\r\n\r\nfileEngine.render('template.ejs', {\r\n    name: 'me'\r\n});\r\n\r\n/* ***output***\r\n\r\nHello me\r\n\r\n*/\r\n```\r\n\r\n## Syntax\r\n* code isolation `<% code %>`\r\n* data printing `<%= data %>` or `<% print(data) %>`\r\n* includes `<%# template %>` or `<% include(template) %>`"}